pyioc/__init__.py
pyioc/containers.py
pyioc/locators.py
pyioc/providers.py
pyioc-0.3.0.dist-info/DESCRIPTION.rst
pyioc-0.3.0.dist-info/METADATA
pyioc-0.3.0.dist-info/RECORD
pyioc-0.3.0.dist-info/WHEEL
pyioc-0.3.0.dist-info/metadata.json
pyioc-0.3.0.dist-info/top_level.txt
