Metadata-Version: 2.0
Name: pyioc
Version: 0.3.0
Summary: Python IoC tools.
Home-page: https://github.com/MrUPGrade/pyioc
Author: Jakub (Mr. UPGrade) Czapliński
Author-email: itsupgradetime@gmail.com
License: MIT
Platform: UNKNOWN
Classifier: Programming Language :: Python :: 2.6
Classifier: Programming Language :: Python :: 2.7
Classifier: Programming Language :: Python :: 3.3
Classifier: Programming Language :: Python :: 3.4
Classifier: Programming Language :: Python :: 3.5
Requires-Dist: enum34 (>=1.1.1)
Requires-Dist: future (>=0.15.2)
Requires-Dist: six (>=1.9.0)
Provides-Extra: dev
Requires-Dist: flake8; extra == 'dev'
Requires-Dist: ipython; extra == 'dev'
Provides-Extra: doc
Requires-Dist: sphinx; extra == 'doc'
Provides-Extra: test
Requires-Dist: coverage (>=4.0.0); extra == 'test'
Requires-Dist: mock (>=1.0.1); extra == 'test'
Requires-Dist: pytest (>=2.7.3); extra == 'test'
